<annotation>
	<folder>n02782093</folder>
	<filename>n02782093_2643</filename>
	<source>
		<database>ImageNet database</database>
	</source>
	<size>
		<width>323</width>
		<height>500</height>
		<depth>3</depth>
	</size>
	<segmented>0</segmented>
	<object>
		<name>n02782093</name>
		<pose>Unspecified</pose>
		<truncated>0</truncated>
		<difficult>0</difficult>
		<bndbox>
			<xmin>35</xmin>
			<ymin>31</ymin>
			<xmax>68</xmax>
			<ymax>85</ymax>
		</bndbox>
	</object>
	<object>
		<name>n02782093</name>
		<pose>Unspecified</pose>
		<truncated>0</truncated>
		<difficult>0</difficult>
		<bndbox>
			<xmin>67</xmin>
			<ymin>239</ymin>
			<xmax>234</xmax>
			<ymax>498</ymax>
		</bndbox>
	</object>
</annotation>