<annotation>
	<folder>n02509815</folder>
	<filename>n02509815_876</filename>
	<source>
		<database>ImageNet database</database>
	</source>
	<size>
		<width>241</width>
		<height>152</height>
		<depth>3</depth>
	</size>
	<segmented>0</segmented>
	<object>
		<name>n02509815</name>
		<pose>Unspecified</pose>
		<truncated>0</truncated>
		<difficult>0</difficult>
		<bndbox>
			<xmin>102</xmin>
			<ymin>13</ymin>
			<xmax>175</xmax>
			<ymax>105</ymax>
		</bndbox>
	</object>
	<object>
		<name>n02509815</name>
		<pose>Unspecified</pose>
		<truncated>0</truncated>
		<difficult>0</difficult>
		<bndbox>
			<xmin>27</xmin>
			<ymin>20</ymin>
			<xmax>103</xmax>
			<ymax>104</ymax>
		</bndbox>
	</object>
</annotation>