<annotation>
	<folder>n02086240</folder>
	<filename>n02086240_3768</filename>
	<source>
		<database>ImageNet database</database>
	</source>
	<size>
		<width>500</width>
		<height>375</height>
		<depth>3</depth>
	</size>
	<segmented>0</segmented>
	<object>
		<name>n02086240</name>
		<pose>Unspecified</pose>
		<truncated>0</truncated>
		<difficult>0</difficult>
		<bndbox>
			<xmin>35</xmin>
			<ymin>46</ymin>
			<xmax>232</xmax>
			<ymax>356</ymax>
		</bndbox>
	</object>
	<object>
		<name>n02086240</name>
		<pose>Unspecified</pose>
		<truncated>0</truncated>
		<difficult>0</difficult>
		<bndbox>
			<xmin>198</xmin>
			<ymin>26</ymin>
			<xmax>402</xmax>
			<ymax>371</ymax>
		</bndbox>
	</object>
</annotation>